oashya/__init__.py
oashya/labels.py
oashya/oashya_fp32.onnx
oashya/oashya_int8.onnx
oashya/tracker.cp310-win_amd64.pyd
oashya/utils.py
oashya-0.0.7.dist-info/METADATA
oashya-0.0.7.dist-info/WHEEL
oashya-0.0.7.dist-info/top_level.txt
oashya-0.0.7.dist-info/RECORD
