Metadata-Version: 2.1
Name: oashya
Version: 0.0.7
Summary: OnmyojiAutoScript for YYS
Home-page: https://github.com/runhey/OnmyojiAutoScript
Author: runhey
Author-email: 2234044577@qq.com
Project-URL: Bug Tracker, https://github.com/runhey/OnmyojiAutoScript/issues
Classifier: Programming Language :: Python :: 3
Classifier: License :: OSI Approved :: MIT License
Classifier: Operating System :: OS Independent
Classifier: Natural Language :: Chinese (Simplified)
Requires-Python: >=3.10
